TOPSIS_Shruti_101803512/TOPSIS_Shruti_101803512.py
TOPSIS_Shruti_101803512/__init__.py
TOPSIS_Shruti_101803512-1.dist-info/LICENCE.txt
TOPSIS_Shruti_101803512-1.dist-info/METADATA
TOPSIS_Shruti_101803512-1.dist-info/WHEEL
TOPSIS_Shruti_101803512-1.dist-info/entry_points.txt
TOPSIS_Shruti_101803512-1.dist-info/top_level.txt
TOPSIS_Shruti_101803512-1.dist-info/RECORD
