Metadata-Version: 2.1
Name: TOPSIS-Shruti-101803512
Version: 1
Summary: A Python pip package to apply topsis approach to rank the entries in a dataset
Home-page: UNKNOWN
Author: Shruti Bansal
License: MIT
Platform: UNKNOWN
Classifier: License :: OSI Approved :: MIT License
Classifier: Programming Language :: Python :: 3
Classifier: Programming Language :: Python :: 3.7
Requires-Dist: numpy
Requires-Dist: pandas
